ymdown/__init__.py
ymdown/ymdown.py
ymdown-0.1.2.dist-info/LICENSE
ymdown-0.1.2.dist-info/METADATA
ymdown-0.1.2.dist-info/WHEEL
ymdown-0.1.2.dist-info/entry_points.txt
ymdown-0.1.2.dist-info/top_level.txt
ymdown-0.1.2.dist-info/RECORD
